swe/__init__.py
swe/airflow/__init__.py
swe/airflow/tools/__init__.py
swe/airflow/tools/converter.py
swe/airflow/tools/enums.py
swe/airflow/tools/func.py
swe/airflow/tools/json.py
swe/airflow/tools/model.py
swe/airflow/tools/storage.py
swe/airflow/tools/hooks/__init__.py
swe/airflow/tools/hooks/postgres_hook.py
swe/airflow/tools/operators/__init__.py
swe/airflow/tools/operators/abstract_operator.py
swe/airflow/tools/operators/execute_database.py
swe/airflow/tools/operators/extract_database.py
swe/airflow/tools/operators/http_operator.py
swe/airflow/tools/operators/update_database.py
swe/airflow/tools/tasks/__init__.py
swe/airflow/tools/tasks/abstract_task.py
swe/airflow/tools/tasks/storage_task.py
tools/__init__.py
tools/converter.py
tools/enums.py
tools/func.py
tools/json.py
tools/model.py
tools/storage.py
tools/hooks/__init__.py
tools/hooks/postgres_hook.py
tools/operators/__init__.py
tools/operators/abstract_operator.py
tools/operators/execute_database.py
tools/operators/extract_database.py
tools/operators/http_operator.py
tools/operators/update_database.py
tools/tasks/__init__.py
tools/tasks/abstract_task.py
tools/tasks/storage_task.py
swe_airflow_tools-0.0.3.dist-info/LICENSE
swe_airflow_tools-0.0.3.dist-info/METADATA
swe_airflow_tools-0.0.3.dist-info/WHEEL
swe_airflow_tools-0.0.3.dist-info/top_level.txt
swe_airflow_tools-0.0.3.dist-info/RECORD
