Metadata-Version: 2.1
Name: swe-airflow-tools
Version: 0.0.3
Summary: Tools for Apache Airflow Application
Home-page: https://github.com/swe-eng-br/swe-airflow-tools
Author: Eduardo Luiz
Author-email: swe@swe.com.br
License: UNKNOWN
Platform: UNKNOWN
Classifier: Programming Language :: Python :: 3
Classifier: License :: OSI Approved :: MIT License
Classifier: Operating System :: OS Independent
